plotchecker/__init__.py
plotchecker/_version.py
plotchecker/barplot.py
plotchecker/base.py
plotchecker/lineplot.py
plotchecker/scatterplot.py
plotchecker/tests/__init__.py
plotchecker/tests/conftest.py
plotchecker/tests/test_barplot.py
plotchecker/tests/test_base.py
plotchecker/tests/test_lineplot.py
plotchecker/tests/test_scatterplot.py
plotchecker-0.2.0.dist-info/LICENSE
plotchecker-0.2.0.dist-info/WHEEL
plotchecker-0.2.0.dist-info/METADATA
plotchecker-0.2.0.dist-info/RECORD
