Metadata-Version: 1.1
Name: plotchecker
Version: 0.2.0
Summary: A set of utilities for testing matplotlib plots in an object-oriented manner.
Home-page: https://github.com/jhamrick/plotchecker
Author: Jessica B. Hamrick
Author-email: jhamrick@berkeley.edu
